{"alpha": ["generic"], "arc": ["generic"], "arm": ["eabi", "oabi"], "arm64": ["generic"], "avr32": ["generic"], "blackfin": ["generic"], "c6x": ["generic"], "cris": ["generic"], "frv": ["generic"], "hexagon": ["generic"], "ia64": ["generic"], "m32r": ["generic"], "m68k": ["generic"], "metag": ["generic"], "microblaze": ["generic"], "mips": ["n32", "n64", "o32"], "mn10300": ["generic"], "nios2": ["generic"], "openrisc": ["generic"], "parisc": ["generic"], "powerpc": ["32", "64"], "s390": ["32", "64"], "score": ["generic"], "sh": ["32", "64"], "sparc": ["32", "64"], "tile": ["generic"], "unicore32": ["generic"], "x86": ["32", "64", "x32"], "xtensa": ["generic"]}